talkto/__init__.py
talkto/admin.py
talkto/apps.py
talkto/forms.py
talkto/serializer.py
talkto/tests.py
talkto/utils.py
talkto/migrations/__init__.py
talkto/models/__init__.py
talkto/models/base.py
talkto/models/managers.py
talkto/views/__init__.py
talkto/views/api.py
talkto/views/base.py
talkto/views/edit.py
djangotalkto-0.1.4.dist-info/LICENSE
djangotalkto-0.1.4.dist-info/METADATA
djangotalkto-0.1.4.dist-info/WHEEL
djangotalkto-0.1.4.dist-info/top_level.txt
djangotalkto-0.1.4.dist-info/RECORD
